OutRemove/OutRemove.py
OutRemove/__init__.py
OutRemove_manav1811kumar-0.0.5.dist-info/LICENSE.txt
OutRemove_manav1811kumar-0.0.5.dist-info/METADATA
OutRemove_manav1811kumar-0.0.5.dist-info/WHEEL
OutRemove_manav1811kumar-0.0.5.dist-info/top_level.txt
OutRemove_manav1811kumar-0.0.5.dist-info/RECORD
